Workbook

Sheet Cover
A1: RETIREMENT PLANNING WORKBOOK
A2: Guide to the forecast, assumptions, Social Security choices, and full calculation model.
A4: CONTENTS
A5: Sheet | B5: Purpose
A6: Retirement Forecast | B6: Readable milestone summary, headline values, and key findings.
A7: Assumptions | B7: Editable return, withdrawal, claiming-age, IRMAA, RMD, and spending inputs.
A8: Social Security | B8: Claiming-age comparison for both spouses, including cumulative benefits.
A9: Projection Data | B9: Complete year-by-year calculation model in $000.

Sheet Projection Data
A1: Section | B1: Description | C1: Input / note | D1: 46387 | E1: 46752 | F1: 47118 | G1: 47483 | H1: 47848 | I1: 48213 | J1: 48579 | K1: 48944 | L1: 49309 | M1: 49674 | N1: 50040 | O1: 50405 | P1: 50770 | Q1: 51135 | R1: 51501 | S1: 51866 | T1: 52231 | U1: 52596 | V1: 52962 | W1: 53327 | X1: 53692 | Y1: 54057 | Z1: 54423 | AA1: 54788 | AB1: 55153 | AC1: 55518 | AD1: 55884 | AE1: 56249 | AF1: 56614
A2: Age | B2: Age | C2: Calculated age | D2: =DATEDIF('Social Security'!$L$5,DATE(YEAR(D$1),12,31),"Y") -> 49 | E2: =DATEDIF('Social Security'!$L$5,DATE(YEAR(E$1),12,31),"Y") -> 50 | F2: =DATEDIF('Social Security'!$L$5,DATE(YEAR(F$1),12,31),"Y") -> 51 | G2: =DATEDIF('Social Security'!$L$5,DATE(YEAR(G$1),12,31),"Y") -> 52 | H2: =DATEDIF('Social Security'!$L$5,DATE(YEAR(H$1),12,31),"Y") -> 53 | I2: =DATEDIF('Social Security'!$L$5,DATE(YEAR(I$1),12,31),"Y") -> 54 | J2: =DATEDIF('Social Security'!$L$5,DATE(YEAR(J$1),12,31),"Y") -> 55 | K2: =DATEDIF('Social Security'!$L$5,DATE(YEAR(K$1),12,31),"Y") -> 56 | ... AF2: =DATEDIF('Social Security'!$L$5,DATE(YEAR(AF$1),12,31),"Y") -> 77
A3: CONVERSION | B3: 401(k) to Roth conversion | C3: Annual $000 | D3: 0 | E3: 0 | F3: 0 | G3: 0 | H3: 0 | I3: 0 | J3: 0 | K3: 0 | L3: 0 | M3: 0 | N3: 0 | O3: 0 | P3: 0 | Q3: 0 | R3: 0 | S3: 0 | T3: 0 | U3: 0 | V3: 0 | W3: 0 | X3: 0 | Y3: 0 | Z3: 0 | AA3: 0 | AB3: 0 | AC3: 0 | AD3: 0 | AE3: 0 | AF3: 0
A4: INPUTS | B4: 401(k) withdrawal | C4: Annual $000 | D4: 0 | E4: 0 | F4: 0 | G4: 0 | H4: 0 | I4: 0 | J4: 0 | K4: 0 | L4: 0 | M4: 0 | N4: 0 | O4: 0 | P4: 0 | Q4: 0 | R4: 0 | S4: 75 | T4: 75 | U4: 75 | V4: 0 | W4: 0 | X4: 0 | Y4: 0 | Z4: 0 | AA4: 0 | AB4: 0 | AC4: 0 | AD4: 0 | AE4: 0 | AF4: 0
A5: INPUTS | B5: W2_Income | C5: Annual $000 | D5: 100 | E5: 100 | F5: 100 | G5: 100 | H5: 100 | I5: 100 | J5: 100 | K5: 100 | L5: 100 | M5: 100 | N5: 100 | O5: 100 | P5: 100 | Q5: 100 | R5: 100 | S5: 0 | T5: 0 | U5: 0 | V5: 0 | W5: 0 | X5: 0 | Y5: 0 | Z5: 0 | AA5: 0 | AB5: 0 | AC5: 0 | AD5: 0 | AE5: 0 | AF5: 0
A6: INPUTS | B6: Rental_Income | C6: Annual $000 | D6: 0 | E6: 0 | F6: 0 | G6: 0 | H6: 0 | I6: 0 | J6: 0 | K6: 0 | L6: 0 | M6: 0 | N6: 0 | O6: 0 | P6: 0 | Q6: 0 | R6: 0 | S6: 0 | T6: 0 | U6: 0 | V6: 0 | W6: 0 | X6: 0 | Y6: 0 | Z6: 0 | AA6: 0 | AB6: 0 | AC6: 0 | AD6: 0 | AE6: 0 | AF6: 0
A7: INPUTS | B7: Annual_SS (C7=claim age) | C7: =Assumptions!B7 -> 67 | D7: =IF(D2<$C$7,0,INDEX('Social Security'!$B$8:$J$8,1,MATCH($C$7,'Social Security'!$B$4:$J$4,0))/1000) -> 0 | E7: =IF(E2<$C$7,0,INDEX('Social Security'!$B$8:$J$8,1,MATCH($C$7,'Social Security'!$B$4:$J$4,0))/1000) -> 0 | F7: =IF(F2<$C$7,0,INDEX('Social Security'!$B$8:$J$8,1,MATCH($C$7,'Social Security'!$B$4:$J$4,0))/1000) -> 0 | G7: =IF(G2<$C$7,0,INDEX('Social Security'!$B$8:$J$8,1,MATCH($C$7,'Social Security'!$B$4:$J$4,0))/1000) -> 0 | H7: =IF(H2<$C$7,0,INDEX('Social Security'!$B$8:$J$8,1,MATCH($C$7,'Social Security'!$B$4:$J$4,0))/1000) -> 0 | I7: =IF(I2<$C$7,0,INDEX('Social Security'!$B$8:$J$8,1,MATCH($C$7,'Social Security'!$B$4:$J$4,0))/1000) -> 0 | J7: =IF(J2<$C$7,0,INDEX('Social Security'!$B$8:$J$8,1,MATCH($C$7,'Social Security'!$B$4:$J$4,0))/1000) -> 0 | K7: =IF(K2<$C$7,0,INDEX('Social Security'!$B$8:$J$8,1,MATCH($C$7,'Social Security'!$B$4:$J$4,0))/1000) -> 0 | ... AF7: =IF(AF2<$C$7,0,INDEX('Social Security'!$B$8:$J$8,1,MATCH($C$7,'Social Security'!$B$4:$J$4,0))/1000) -> 65.628
A8: INPUTS | B8: Annual_RMD | C8: Calculated | D8: =IF(D2>=75,D25/VLOOKUP(D2,Assumptions!$A$11:$B$34,2,FALSE),0) -> 0 | E8: =IF(E2>=75,E25/VLOOKUP(E2,Assumptions!$A$11:$B$34,2,FALSE),0) -> 0 | F8: =IF(F2>=75,F25/VLOOKUP(F2,Assumptions!$A$11:$B$34,2,FALSE),0) -> 0 | G8: =IF(G2>=75,G25/VLOOKUP(G2,Assumptions!$A$11:$B$34,2,FALSE),0) -> 0 | H8: =IF(H2>=75,H25/VLOOKUP(H2,Assumptions!$A$11:$B$34,2,FALSE),0) -> 0 | I8: =IF(I2>=75,I25/VLOOKUP(I2,Assumptions!$A$11:$B$34,2,FALSE),0) -> 0 | J8: =IF(J2>=75,J25/VLOOKUP(J2,Assumptions!$A$11:$B$34,2,FALSE),0) -> 0 | K8: =IF(K2>=75,K25/VLOOKUP(K2,Assumptions!$A$11:$B$34,2,FALSE),0) -> 0 | ... AF8: =IF(AF2>=75,AF25/VLOOKUP(AF2,Assumptions!$A$11:$B$34,2,FALSE),0) -> 80.79918
A9: INPUTS | B9: Brokerage LTCG | C9: Annual $000 | D9: 0 | E9: 0 | F9: 0 | G9: 0 | H9: 0 | I9: 0 | J9: 0 | K9: 0 | L9: 0 | M9: 0 | N9: 0 | O9: 0 | P9: 0 | Q9: 0 | R9: 0 | S9: 0 | T9: 0 | U9: 0 | V9: 0 | W9: 0 | X9: 0 | Y9: 0 | Z9: 0 | AA9: 0 | AB9: 0 | AC9: 0 | AD9: 0 | AE9: 0 | AF9: 0
A10: INPUTS | B10: SLC LTCG | C10: Annual $000 | D10: 0 | E10: 0 | F10: 0 | G10: 0 | H10: 0 | I10: 0 | J10: 0 | K10: 0 | L10: 0 | M10: 0 | N10: 0 | O10: 0 | P10: 0 | Q10: 0 | R10: 0 | S10: 0 | T10: 0 | U10: 0 | V10: 0 | W10: 0 | X10: 0 | Y10: 0 | Z10: 0 | AA10: 0 | AB10: 0 | AC10: 0 | AD10: 0 | AE10: 0 | AF10: 0
A11: INPUTS | B11: ROTH IRA | C11: Annual $000 | D11: 0 | E11: 0 | F11: 0 | G11: 0 | H11: 0 | I11: 0 | J11: 0 | K11: 0 | L11: 0 | M11: 0 | N11: 0 | O11: 0 | P11: 0 | Q11: 0 | R11: 0 | S11: 0 | T11: 0 | U11: 0 | V11: 0 | W11: 0 | X11: 0 | Y11: 0 | Z11: 0 | AA11: 0 | AB11: 0 | AC11: 0 | AD11: 0 | AE11: 0 | AF11: 0
A12: CALCULATIONS | B12: Total_Ordinary_Gross | C12: Calculated | D12: =D3+D4+D5+D6+D8 -> 100 | E12: =E3+E4+E5+E6+E8 -> 100 | F12: =F3+F4+F5+F6+F8 -> 100 | G12: =G3+G4+G5+G6+G8 -> 100 | H12: =H3+H4+H5+H6+H8 -> 100 | I12: =I3+I4+I5+I6+I8 -> 100 | J12: =J3+J4+J5+J6+J8 -> 100 | K12: =K3+K4+K5+K6+K8 -> 100 | ... AF12: =AF3+AF4+AF5+AF6+AF8 -> 80.79918
A13: SS TAXABILITY | B13: Provisional_Income_Approx | C13: Calculated | D13: =D12+D17+D7*0.5 -> 100 | E13: =E12+E17+E7*0.5 -> 100 | F13: =F12+F17+F7*0.5 -> 100 | G13: =G12+G17+G7*0.5 -> 100 | H13: =H12+H17+H7*0.5 -> 100 | I13: =I12+I17+I7*0.5 -> 100 | J13: =J12+J17+J7*0.5 -> 100 | K13: =K12+K17+K7*0.5 -> 100 | ... AF13: =AF12+AF17+AF7*0.5 -> 113.61318
A14: SS TAXABILITY | B14: Taxable_SS_% | C14: Calculated | D14: =IF(D13<32,0,IF(D13<44,0.5,0.85)) -> 0.85 | E14: =IF(E13<32,0,IF(E13<44,0.5,0.85)) -> 0.85 | F14: =IF(F13<32,0,IF(F13<44,0.5,0.85)) -> 0.85 | G14: =IF(G13<32,0,IF(G13<44,0.5,0.85)) -> 0.85 | H14: =IF(H13<32,0,IF(H13<44,0.5,0.85)) -> 0.85 | I14: =IF(I13<32,0,IF(I13<44,0.5,0.85)) -> 0.85 | J14: =IF(J13<32,0,IF(J13<44,0.5,0.85)) -> 0.85 | K14: =IF(K13<32,0,IF(K13<44,0.5,0.85)) -> 0.85 | ... AF14: =IF(AF13<32,0,IF(AF13<44,0.5,0.85)) -> 0.85
A15: SS TAXABILITY | B15: Taxable_SS_$ | C15: Calculated | D15: =D7*D14 -> 0 | E15: =E7*E14 -> 0 | F15: =F7*F14 -> 0 | G15: =G7*G14 -> 0 | H15: =H7*H14 -> 0 | I15: =I7*I14 -> 0 | J15: =J7*J14 -> 0 | K15: =K7*K14 -> 0 | ... AF15: =AF7*AF14 -> 55.7838
A16: Ordinary Income | B16: Total_Taxable_Ordinary | C16: Calculated | D16: =D12+D15 -> 100 | E16: =E12+E15 -> 100 | F16: =F12+F15 -> 100 | G16: =G12+G15 -> 100 | H16: =H12+H15 -> 100 | I16: =I12+I15 -> 100 | J16: =J12+J15 -> 100 | K16: =K12+K15 -> 100 | ... AF16: =AF12+AF15 -> 136.58298
A17: LTCG | B17: Total Taxable LTCG | C17: Calculated | D17: =D9+D10 -> 0 | E17: =E9+E10 -> 0 | F17: =F9+F10 -> 0 | G17: =G9+G10 -> 0 | H17: =H9+H10 -> 0 | I17: =I9+I10 -> 0 | J17: =J9+J10 -> 0 | K17: =K9+K10 -> 0 | ... AF17: =AF9+AF10 -> 0
A18: =SUM(D18:AF18) -> 163.65058 | B18: Total_Federal_Tax | C18: Calculated | D18: =_xlfn.LET(_xlpm.o,D16,_xlpm.g,D17,_xlpm.t,MAX(0,_xlpm.o-32.2),_xlpm.x,MAX(0,MIN(_xlpm.t,24.8))*0.1+MAX(0,MIN(_xlpm.t,100.8)-24.8)*0.12+MAX(0,MIN(_xlpm.t,211.4)-100.8)*0.22+MAX(0,MIN(_xlpm.t,403.55)-211.4)*0.24+MAX(0,MIN(_xlpm.t,512.45)-403.55)*0.32+MAX(0,MIN(_xlpm.t,768.7)-512.45)*0.35+MAX(0,_xlpm.t-768.7)*0.37,_xlpm.a,MIN(_xlpm.g,MAX(0,98.4-_xlpm.t)),_xlpm.b,MIN(_xlpm.g-_xlpm.a,MAX(0,613.7-MAX(_xlpm.t,98.4))),_xlpm.x+_xlpm.b*0.15+(_xlpm.g-_xlpm.a-_xlpm.b)*0.2+MIN(_xlpm.g+D6,MAX(0,_xlpm.o+_xlpm.g-250))*0.038) -> 7.64 | E18: =_xlfn.LET(_xlpm.o,E16,_xlpm.g,E17,_xlpm.t,MAX(0,_xlpm.o-32.2),_xlpm.x,MAX(0,MIN(_xlpm.t,24.8))*0.1+MAX(0,MIN(_xlpm.t,100.8)-24.8)*0.12+MAX(0,MIN(_xlpm.t,211.4)-100.8)*0.22+MAX(0,MIN(_xlpm.t,403.55)-211.4)*0.24+MAX(0,MIN(_xlpm.t,512.45)-403.55)*0.32+MAX(0,MIN(_xlpm.t,768.7)-512.45)*0.35+MAX(0,_xlpm.t-768.7)*0.37,_xlpm.a,MIN(_xlpm.g,MAX(0,98.4-_xlpm.t)),_xlpm.b,MIN(_xlpm.g-_xlpm.a,MAX(0,613.7-MAX(_xlpm.t,98.4))),_xlpm.x+_xlpm.b*0.15+(_xlpm.g-_xlpm.a-_xlpm.b)*0.2+MIN(_xlpm.g+E6,MAX(0,_xlpm.o+_xlpm.g-250))*0.038) -> 7.64 | F18: =_xlfn.LET(_xlpm.o,F16,_xlpm.g,F17,_xlpm.t,MAX(0,_xlpm.o-32.2),_xlpm.x,MAX(0,MIN(_xlpm.t,24.8))*0.1+MAX(0,MIN(_xlpm.t,100.8)-24.8)*0.12+MAX(0,MIN(_xlpm.t,211.4)-100.8)*0.22+MAX(0,MIN(_xlpm.t,403.55)-211.4)*0.24+MAX(0,MIN(_xlpm.t,512.45)-403.55)*0.32+MAX(0,MIN(_xlpm.t,768.7)-512.45)*0.35+MAX(0,_xlpm.t-768.7)*0.37,_xlpm.a,MIN(_xlpm.g,MAX(0,98.4-_xlpm.t)),_xlpm.b,MIN(_xlpm.g-_xlpm.a,MAX(0,613.7-MAX(_xlpm.t,98.4))),_xlpm.x+_xlpm.b*0.15+(_xlpm.g-_xlpm.a-_xlpm.b)*0.2+MIN(_xlpm.g+F6,MAX(0,_xlpm.o+_xlpm.g-250))*0.038) -> 7.64 | G18: =_xlfn.LET(_xlpm.o,G16,_xlpm.g,G17,_xlpm.t,MAX(0,_xlpm.o-32.2),_xlpm.x,MAX(0,MIN(_xlpm.t,24.8))*0.1+MAX(0,MIN(_xlpm.t,100.8)-24.8)*0.12+MAX(0,MIN(_xlpm.t,211.4)-100.8)*0.22+MAX(0,MIN(_xlpm.t,403.55)-211.4)*0.24+MAX(0,MIN(_xlpm.t,512.45)-403.55)*0.32+MAX(0,MIN(_xlpm.t,768.7)-512.45)*0.35+MAX(0,_xlpm.t-768.7)*0.37,_xlpm.a,MIN(_xlpm.g,MAX(0,98.4-_xlpm.t)),_xlpm.b,MIN(_xlpm.g-_xlpm.a,MAX(0,613.7-MAX(_xlpm.t,98.4))),_xlpm.x+_xlpm.b*0.15+(_xlpm.g-_xlpm.a-_xlpm.b)*0.2+MIN(_xlpm.g+G6,MAX(0,_xlpm.o+_xlpm.g-250))*0.038) -> 7.64 | H18: =_xlfn.LET(_xlpm.o,H16,_xlpm.g,H17,_xlpm.t,MAX(0,_xlpm.o-32.2),_xlpm.x,MAX(0,MIN(_xlpm.t,24.8))*0.1+MAX(0,MIN(_xlpm.t,100.8)-24.8)*0.12+MAX(0,MIN(_xlpm.t,211.4)-100.8)*0.22+MAX(0,MIN(_xlpm.t,403.55)-211.4)*0.24+MAX(0,MIN(_xlpm.t,512.45)-403.55)*0.32+MAX(0,MIN(_xlpm.t,768.7)-512.45)*0.35+MAX(0,_xlpm.t-768.7)*0.37,_xlpm.a,MIN(_xlpm.g,MAX(0,98.4-_xlpm.t)),_xlpm.b,MIN(_xlpm.g-_xlpm.a,MAX(0,613.7-MAX(_xlpm.t,98.4))),_xlpm.x+_xlpm.b*0.15+(_xlpm.g-_xlpm.a-_xlpm.b)*0.2+MIN(_xlpm.g+H6,MAX(0,_xlpm.o+_xlpm.g-250))*0.038) -> 7.64 | I18: =_xlfn.LET(_xlpm.o,I16,_xlpm.g,I17,_xlpm.t,MAX(0,_xlpm.o-32.2),_xlpm.x,MAX(0,MIN(_xlpm.t,24.8))*0.1+MAX(0,MIN(_xlpm.t,100.8)-24.8)*0.12+MAX(0,MIN(_xlpm.t,211.4)-100.8)*0.22+MAX(0,MIN(_xlpm.t,403.55)-211.4)*0.24+MAX(0,MIN(_xlpm.t,512.45)-403.55)*0.32+MAX(0,MIN(_xlpm.t,768.7)-512.45)*0.35+MAX(0,_xlpm.t-768.7)*0.37,_xlpm.a,MIN(_xlpm.g,MAX(0,98.4-_xlpm.t)),_xlpm.b,MIN(_xlpm.g-_xlpm.a,MAX(0,613.7-MAX(_xlpm.t,98.4))),_xlpm.x+_xlpm.b*0.15+(_xlpm.g-_xlpm.a-_xlpm.b)*0.2+MIN(_xlpm.g+I6,MAX(0,_xlpm.o+_xlpm.g-250))*0.038) -> 7.64 | J18: =_xlfn.LET(_xlpm.o,J16,_xlpm.g,J17,_xlpm.t,MAX(0,_xlpm.o-32.2),_xlpm.x,MAX(0,MIN(_xlpm.t,24.8))*0.1+MAX(0,MIN(_xlpm.t,100.8)-24.8)*0.12+MAX(0,MIN(_xlpm.t,211.4)-100.8)*0.22+MAX(0,MIN(_xlpm.t,403.55)-211.4)*0.24+MAX(0,MIN(_xlpm.t,512.45)-403.55)*0.32+MAX(0,MIN(_xlpm.t,768.7)-512.45)*0.35+MAX(0,_xlpm.t-768.7)*0.37,_xlpm.a,MIN(_xlpm.g,MAX(0,98.4-_xlpm.t)),_xlpm.b,MIN(_xlpm.g-_xlpm.a,MAX(0,613.7-MAX(_xlpm.t,98.4))),_xlpm.x+_xlpm.b*0.15+(_xlpm.g-_xlpm.a-_xlpm.b)*0.2+MIN(_xlpm.g+J6,MAX(0,_xlpm.o+_xlpm.g-250))*0.038) -> 7.64 | K18: =_xlfn.LET(_xlpm.o,K16,_xlpm.g,K17,_xlpm.t,MAX(0,_xlpm.o-32.2),_xlpm.x,MAX(0,MIN(_xlpm.t,24.8))*0.1+MAX(0,MIN(_xlpm.t,100.8)-24.8)*0.12+MAX(0,MIN(_xlpm.t,211.4)-100.8)*0.22+MAX(0,MIN(_xlpm.t,403.55)-211.4)*0.24+MAX(0,MIN(_xlpm.t,512.45)-403.55)*0.32+MAX(0,MIN(_xlpm.t,768.7)-512.45)*0.35+MAX(0,_xlpm.t-768.7)*0.37,_xlpm.a,MIN(_xlpm.g,MAX(0,98.4-_xlpm.t)),_xlpm.b,MIN(_xlpm.g-_xlpm.a,MAX(0,613.7-MAX(_xlpm.t,98.4))),_xlpm.x+_xlpm.b*0.15+(_xlpm.g-_xlpm.a-_xlpm.b)*0.2+MIN(_xlpm.g+K6,MAX(0,_xlpm.o+_xlpm.g-250))*0.038) -> 7.64 | ... AF18: =_xlfn.LET(_xlpm.o,AF16,_xlpm.g,AF17,_xlpm.t,MAX(0,_xlpm.o-32.2),_xlpm.x,MAX(0,MIN(_xlpm.t,24.8))*0.1+MAX(0,MIN(_xlpm.t,100.8)-24.8)*0.12+MAX(0,MIN(_xlpm.t,211.4)-100.8)*0.22+MAX(0,MIN(_xlpm.t,403.55)-211.4)*0.24+MAX(0,MIN(_xlpm.t,512.45)-403.55)*0.32+MAX(0,MIN(_xlpm.t,768.7)-512.45)*0.35+MAX(0,_xlpm.t-768.7)*0.37,_xlpm.a,MIN(_xlpm.g,MAX(0,98.4-_xlpm.t)),_xlpm.b,MIN(_xlpm.g-_xlpm.a,MAX(0,613.7-MAX(_xlpm.t,98.4))),_xlpm.x+_xlpm.b*0.15+(_xlpm.g-_xlpm.a-_xlpm.b)*0.2+MIN(_xlpm.g+AF6,MAX(0,_xlpm.o+_xlpm.g-250))*0.038) -> 12.388256
A19: SUMMARY | B19: MAGI_IRMAA | C19: Calculated | D19: =D16+D17 -> 100 | E19: =E16+E17 -> 100 | F19: =F16+F17 -> 100 | G19: =G16+G17 -> 100 | H19: =H16+H17 -> 100 | I19: =I16+I17 -> 100 | J19: =J16+J17 -> 100 | K19: =K16+K17 -> 100 | ... AF19: =AF16+AF17 -> 136.58298
A20: SUMMARY | B20: IRMAA_Status | C20: Calculated | D20: {=IF(D2<65,IF(D19<=Assumptions!$B$8,"✅ SAFE - $0 IRMAA","⚠️ IRMAA"),IF(INDEX($D$19:$AF$19,1,MAX(1,COLUMN()-COLUMN($D$19)-1))<=Assumptions!$B$8,"✅ SAFE - $0 IRMAA","⚠️ IRMAA"))} -> ✅ SAFE - $0 IRMAA | E20: {=IF(E2<65,IF(E19<=Assumptions!$B$8,"✅ SAFE - $0 IRMAA","⚠️ IRMAA"),IF(INDEX($D$19:$AF$19,1,MAX(1,COLUMN()-COLUMN($D$19)-1))<=Assumptions!$B$8,"✅ SAFE - $0 IRMAA","⚠️ IRMAA"))} -> ✅ SAFE - $0 IRMAA | F20: {=IF(F2<65,IF(F19<=Assumptions!$B$8,"✅ SAFE - $0 IRMAA","⚠️ IRMAA"),IF(INDEX($D$19:$AF$19,1,MAX(1,COLUMN()-COLUMN($D$19)-1))<=Assumptions!$B$8,"✅ SAFE - $0 IRMAA","⚠️ IRMAA"))} -> ✅ SAFE - $0 IRMAA | G20: {=IF(G2<65,IF(G19<=Assumptions!$B$8,"✅ SAFE - $0 IRMAA","⚠️ IRMAA"),IF(INDEX($D$19:$AF$19,1,MAX(1,COLUMN()-COLUMN($D$19)-1))<=Assumptions!$B$8,"✅ SAFE - $0 IRMAA","⚠️ IRMAA"))} -> ✅ SAFE - $0 IRMAA | H20: {=IF(H2<65,IF(H19<=Assumptions!$B$8,"✅ SAFE - $0 IRMAA","⚠️ IRMAA"),IF(INDEX($D$19:$AF$19,1,MAX(1,COLUMN()-COLUMN($D$19)-1))<=Assumptions!$B$8,"✅ SAFE - $0 IRMAA","⚠️ IRMAA"))} -> ✅ SAFE - $0 IRMAA | I20: {=IF(I2<65,IF(I19<=Assumptions!$B$8,"✅ SAFE - $0 IRMAA","⚠️ IRMAA"),IF(INDEX($D$19:$AF$19,1,MAX(1,COLUMN()-COLUMN($D$19)-1))<=Assumptions!$B$8,"✅ SAFE - $0 IRMAA","⚠️ IRMAA"))} -> ✅ SAFE - $0 IRMAA | J20: {=IF(J2<65,IF(J19<=Assumptions!$B$8,"✅ SAFE - $0 IRMAA","⚠️ IRMAA"),IF(INDEX($D$19:$AF$19,1,MAX(1,COLUMN()-COLUMN($D$19)-1))<=Assumptions!$B$8,"✅ SAFE - $0 IRMAA","⚠️ IRMAA"))} -> ✅ SAFE - $0 IRMAA | K20: {=IF(K2<65,IF(K19<=Assumptions!$B$8,"✅ SAFE - $0 IRMAA","⚠️ IRMAA"),IF(INDEX($D$19:$AF$19,1,MAX(1,COLUMN()-COLUMN($D$19)-1))<=Assumptions!$B$8,"✅ SAFE - $0 IRMAA","⚠️ IRMAA"))} -> ✅ SAFE - $0 IRMAA | ... AF20: {=IF(AF2<65,IF(AF19<=Assumptions!$B$8,"✅ SAFE - $0 IRMAA","⚠️ IRMAA"),IF(INDEX($D$19:$AF$19,1,MAX(1,COLUMN()-COLUMN($D$19)-1))<=Assumptions!$B$8,"✅ SAFE - $0 IRMAA","⚠️ IRMAA"))} -> ✅ SAFE - $0 IRMAA
A21: SUMMARY | B21: Total_Cash_in | C21: Calculated | D21: =SUM(D4:D11) -> 100 | E21: =SUM(E4:E11) -> 100 | F21: =SUM(F4:F11) -> 100 | G21: =SUM(G4:G11) -> 100 | H21: =SUM(H4:H11) -> 100 | I21: =SUM(I4:I11) -> 100 | J21: =SUM(J4:J11) -> 100 | K21: =SUM(K4:K11) -> 100 | ... AF21: =SUM(AF4:AF11) -> 146.42718
A22: CASH FLOW | B22: CashFlow_AfterTax | C22: Calculated | D22: =D21 - D18 - D31 -> 92.36 | E22: =E21 - E18 - E31 -> 86.36 | F22: =F21 - F18 - F31 -> 86.36 | G22: =G21 - G18 - G31 -> 86.36 | H22: =H21 - H18 - H31 -> 86.36 | I22: =I21 - I18 - I31 -> 86.36 | J22: =J21 - J18 - J31 -> 86.36 | K22: =K21 - K18 - K31 -> 86.36 | ... AF22: =AF21 - AF18 - AF31 -> 134.03892
A23: CASH FLOW | B23: Monthly_CashFlow | C23: Calculated | D23: =D22/12 -> 7.6966667 | E23: =E22/12 -> 7.1966667 | F23: =F22/12 -> 7.1966667 | G23: =G22/12 -> 7.1966667 | H23: =H22/12 -> 7.1966667 | I23: =I22/12 -> 7.1966667 | J23: =J22/12 -> 7.1966667 | K23: =K22/12 -> 7.1966667 | ... AF23: =AF22/12 -> 11.16991
A24: =AF24 -> 1786.484 | B24: Brokerage | C24: Calculated | D24: 200 | E24: =D24*(1+$A$28)-E9+E31-E30+E32 -> 220.5 | F24: =E24*(1+$A$28)-F9+F31-F30+F32 -> 242.48625 | G24: =F24*(1+$A$28)-G9+G31-G30+G32 -> 266.0665 | H24: =G24*(1+$A$28)-H9+H31-H30+H32 -> 291.35632 | I24: =H24*(1+$A$28)-I9+I31-I30+I32 -> 318.47966 | J24: =I24*(1+$A$28)-J9+J31-J30+J32 -> 347.56943 | K24: =J24*(1+$A$28)-K9+K31-K30+K32 -> 378.76822 | L24: =K24*(1+$A$28)-L9+L31-L30+L32 -> 412.22891 | ... AF24: =AE24*(1+$A$28)-AF9+AF31-AF30+AF32 -> 1786.484
A25: =AF25 -> 1850.3012 | B25: 401(k) balance | C25: Calculated | D25: 350 | E25: =D25*(1+$A$28)-E3-E4+E33-D8 -> 381.375 | F25: =E25*(1+$A$28)-F3-F4+IF(F5>149,18,0)-E8 -> 409.02469 | G25: =F25*(1+$A$28)-G3-G4+IF(G5>149,18,0)-F8 -> 438.67898 | H25: =G25*(1+$A$28)-H3-H4+IF(H5>149,18,0)-G8 -> 470.4832 | I25: =H25*(1+$A$28)-I3-I4+IF(I5>149,18,0)-H8 -> 504.59324 | J25: =I25*(1+$A$28)-J3-J4+IF(J5>149,18,0)-I8 -> 541.17625 | K25: =J25*(1+$A$28)-K3-K4+IF(K5>149,18,0)-J8 -> 580.41152 | L25: =K25*(1+$A$28)-L3-L4+IF(L5>149,18,0)-K8 -> 622.49136 | M25: =L25*(1+$A$28)-M3-M4+IF(M5>149,18,0)-L8 -> 667.62198 | ... AF25: =AE25*(1+$A$28)-AF3-AF4+IF(AF5>149,18,0)-AE8 -> 1850.3012
A26: =AF26 -> 1051.8427 | B26: ROTH IRA | C26: Calculated | D26: 0 | E26: =D26*(1+$A$28)+E3+IF(E5>0,17.2,0)-E11 -> 17.2 | F26: =E26*(1+$A$28)+F3+IF(F5>0,17.2,0)-F11 -> 35.647 | G26: =F26*(1+$A$28)+G3+IF(G5>0,17.2,0)-G11 -> 55.431407 | H26: =G26*(1+$A$28)+H3+IF(H5>0,17.2,0)-H11 -> 76.650185 | I26: =H26*(1+$A$28)+I3+IF(I5>0,17.2,0)-I11 -> 99.407323 | J26: =I26*(1+$A$28)+J3+IF(J5>0,17.2,0)-J11 -> 123.81435 | K26: =J26*(1+$A$28)+K3+IF(K5>0,17.2,0)-K11 -> 149.99089 | L26: =K26*(1+$A$28)+L3+IF(L5>0,17.2,0)-L11 -> 178.06523 | ... AF26: =AE26*(1+$A$28)+AF3+IF(AF5>0,17.2,0)-AF11 -> 1051.8427
A27: =AF27 -> 4688.6279 | B27: Savings | C27: Calculated | D27: =D24+D25+D26 -> 550 | E27: =E24+E25+E26 -> 619.075 | F27: =F24+F25+F26 -> 687.15794 | G27: =G24+G25+G26 -> 760.17689 | H27: =H24+H25+H26 -> 838.48971 | I27: =I24+I25+I26 -> 922.48022 | J27: =J24+J25+J26 -> 1012.56 | K27: =K24+K25+K26 -> 1109.1706 | ... AF27: =AF24+AF25+AF26 -> 4688.6279
A28: =Assumptions!B5 -> 0.0725 | B28: Potential annual withdrawal | C28: =Assumptions!B6 -> 0.04 | D28: =D27*$C$28 -> 22 | E28: =E27*$C$28 -> 24.763 | F28: =F27*$C$28 -> 27.486318 | G28: =G27*$C$28 -> 30.407076 | H28: =H27*$C$28 -> 33.539588 | I28: =I27*$C$28 -> 36.899209 | J28: =J27*$C$28 -> 40.502401 | K28: =K27*$C$28 -> 44.366825 | ... AF28: =AF27*$C$28 -> 187.54512
B29: Tax Rate | C29: Calculated | D29: =IF(D16+D17=0,0,D18/(D16+D17)) -> 0.0764 | E29: =IF(E16+E17=0,0,E18/(E16+E17)) -> 0.0764 | F29: =IF(F16+F17=0,0,F18/(F16+F17)) -> 0.0764 | G29: =IF(G16+G17=0,0,G18/(G16+G17)) -> 0.0764 | H29: =IF(H16+H17=0,0,H18/(H16+H17)) -> 0.0764 | I29: =IF(I16+I17=0,0,I18/(I16+I17)) -> 0.0764 | J29: =IF(J16+J17=0,0,J18/(J16+J17)) -> 0.0764 | K29: =IF(K16+K17=0,0,K18/(K16+K17)) -> 0.0764 | ... AF29: =IF(AF16+AF17=0,0,AF18/(AF16+AF17)) -> 0.090701313
B30: Cash Reserves | C30: Annual $000 | D30: =IF(D22>$G$39,0,($G$39-D22)) -> 0 | E30: =IF(E22>$G$39,0,($G$39-E22)) -> 0 | F30: =IF(F22>$G$39,0,($G$39-F22)) -> 0 | G30: =IF(G22>$G$39,0,($G$39-G22)) -> 0 | H30: 0 | I30: =IF(I22>$G$39,0,($G$39-I22)) -> 0 | J30: =IF(J22>$G$39,0,($G$39-J22)) -> 0 | K30: =IF(K22>$G$39,0,($G$39-K22)) -> 0 | L30: =IF(L22>$G$39,0,($G$39-L22)) -> 0 | M30: =IF(M22>$G$39,0,($G$39-M22)) -> 0 | N30: =IF(N22>$G$39,0,($G$39-N22)) -> 0 | O30: =IF(O22>$G$39,0,($G$39-O22)) -> 0 | P30: =IF(P22>$G$39,0,($G$39-P22)) -> 0 | ... AF30: =IF(AF22>$G$39,0,($G$39-AF22)) -> 0
B31: From W2 to Brokerage | C31: Annual $000 | D31: 0 | E31: 6 | F31: 6 | G31: 6 | H31: 6 | I31: 6 | J31: 6 | K31: 6 | L31: 6 | M31: 6 | N31: 6 | O31: 6 | P31: 6 | Q31: 6 | R31: 6 | S31: 0 | T31: 0 | U31: 0 | V31: 0 | W31: 0 | X31: 0 | Y31: 0 | Z31: 0 | AA31: 0 | AB31: 0 | AC31: 0 | AD31: 0 | AE31: 0 | AF31: 0
B32: Non W2 to Brokerage | C32: Annual $000 | D32: 0 | E32: 0 | F32: 0 | G32: 0 | H32: 0 | I32: 0 | J32: 0 | K32: 0 | L32: 0 | M32: 0 | N32: 0 | O32: 0 | P32: 0 | Q32: 0 | R32: 0 | S32: 0 | T32: 0 | U32: 0 | V32: 0 | W32: 0 | X32: 0 | Y32: 0 | Z32: 0 | AA32: 0 | AB32: 0 | AC32: 0 | AD32: 0 | AE32: 0 | AF32: 0
B33: 401K Contribution | C33: Annual $000 | D33: 0 | E33: 6 | F33: 6 | G33: 6 | H33: 6 | I33: 6 | J33: 6 | K33: 6 | L33: 6 | M33: 6 | N33: 6 | O33: 6 | P33: 6 | Q33: 6 | R33: 6 | S33: 0 | T33: 0 | U33: 0 | V33: 0 | W33: 0 | X33: 0 | Y33: 0 | Z33: 0 | AA33: 0 | AB33: 0 | AC33: 0 | AD33: 0 | AE33: 0 | AF33: 0

Sheet Retirement Forecast
A1: RETIREMENT FORECAST — AT A GLANCE
A2: Key milestones in actual dollars; edit highlighted inputs on the Assumptions sheet.
A4: Savings at age 77 | B4: Monthly cash at 67 | C4: First RMD at 75 | D4: IRMAA status at 75
A5: ='Projection Data'!AF27*1000 -> 4688627.9 | B5: =INDEX('Projection Data'!$D$23:$AF$23,1,MATCH(67,'Projection Data'!$D$2:$AF$2,0))*1000 -> 5463.8833 | C5: =INDEX('Projection Data'!$D$8:$AF$8,1,MATCH(75,'Projection Data'!$D$2:$AF$2,0))*1000 -> 70749.722 | D5: =INDEX('Projection Data'!$D$20:$AF$20,1,MATCH(75,'Projection Data'!$D$2:$AF$2,0)) -> ✅ SAFE - $0 IRMAA
A8: MILESTONE PROJECTION
A9: Age | B9: Year | C9: Cash in | D9: Federal tax | E9: After-tax / month | F9: Total savings | G9: 4% withdrawal | H9: IRMAA status
A10: 49 | B10: =INDEX('Projection Data'!$D$1:$AF$1,1,MATCH(A10,'Projection Data'!$D$2:$AF$2,0)) -> 46387 | C10: =INDEX('Projection Data'!$D$21:$AF$21,1,MATCH(A10,'Projection Data'!$D$2:$AF$2,0))*1000 -> 100000 | D10: =INDEX('Projection Data'!$D$18:$AF$18,1,MATCH(A10,'Projection Data'!$D$2:$AF$2,0))*1000 -> 7640 | E10: =INDEX('Projection Data'!$D$23:$AF$23,1,MATCH(A10,'Projection Data'!$D$2:$AF$2,0))*1000 -> 7696.6667 | F10: =INDEX('Projection Data'!$D$27:$AF$27,1,MATCH(A10,'Projection Data'!$D$2:$AF$2,0))*1000 -> 550000 | G10: =INDEX('Projection Data'!$D$28:$AF$28,1,MATCH(A10,'Projection Data'!$D$2:$AF$2,0))*1000 -> 22000 | H10: =INDEX('Projection Data'!$D$20:$AF$20,1,MATCH(A10,'Projection Data'!$D$2:$AF$2,0)) -> ✅ SAFE - $0 IRMAA
A11: 55 | B11: =INDEX('Projection Data'!$D$1:$AF$1,1,MATCH(A11,'Projection Data'!$D$2:$AF$2,0)) -> 48579 | C11: =INDEX('Projection Data'!$D$21:$AF$21,1,MATCH(A11,'Projection Data'!$D$2:$AF$2,0))*1000 -> 100000 | D11: =INDEX('Projection Data'!$D$18:$AF$18,1,MATCH(A11,'Projection Data'!$D$2:$AF$2,0))*1000 -> 7640 | E11: =INDEX('Projection Data'!$D$23:$AF$23,1,MATCH(A11,'Projection Data'!$D$2:$AF$2,0))*1000 -> 7196.6667 | F11: =INDEX('Projection Data'!$D$27:$AF$27,1,MATCH(A11,'Projection Data'!$D$2:$AF$2,0))*1000 -> 1012560 | G11: =INDEX('Projection Data'!$D$28:$AF$28,1,MATCH(A11,'Projection Data'!$D$2:$AF$2,0))*1000 -> 40502.401 | H11: =INDEX('Projection Data'!$D$20:$AF$20,1,MATCH(A11,'Projection Data'!$D$2:$AF$2,0)) -> ✅ SAFE - $0 IRMAA
A12: 60 | B12: =INDEX('Projection Data'!$D$1:$AF$1,1,MATCH(A12,'Projection Data'!$D$2:$AF$2,0)) -> 50405 | C12: =INDEX('Projection Data'!$D$21:$AF$21,1,MATCH(A12,'Projection Data'!$D$2:$AF$2,0))*1000 -> 100000 | D12: =INDEX('Projection Data'!$D$18:$AF$18,1,MATCH(A12,'Projection Data'!$D$2:$AF$2,0))*1000 -> 7640 | E12: =INDEX('Projection Data'!$D$23:$AF$23,1,MATCH(A12,'Projection Data'!$D$2:$AF$2,0))*1000 -> 7196.6667 | F12: =INDEX('Projection Data'!$D$27:$AF$27,1,MATCH(A12,'Projection Data'!$D$2:$AF$2,0))*1000 -> 1570920.6 | G12: =INDEX('Projection Data'!$D$28:$AF$28,1,MATCH(A12,'Projection Data'!$D$2:$AF$2,0))*1000 -> 62836.823 | H12: =INDEX('Projection Data'!$D$20:$AF$20,1,MATCH(A12,'Projection Data'!$D$2:$AF$2,0)) -> ✅ SAFE - $0 IRMAA
A13: 65 | B13: =INDEX('Projection Data'!$D$1:$AF$1,1,MATCH(A13,'Projection Data'!$D$2:$AF$2,0)) -> 52231 | C13: =INDEX('Projection Data'!$D$21:$AF$21,1,MATCH(A13,'Projection Data'!$D$2:$AF$2,0))*1000 -> 75000 | D13: =INDEX('Projection Data'!$D$18:$AF$18,1,MATCH(A13,'Projection Data'!$D$2:$AF$2,0))*1000 -> 4640 | E13: =INDEX('Projection Data'!$D$23:$AF$23,1,MATCH(A13,'Projection Data'!$D$2:$AF$2,0))*1000 -> 5863.3333 | F13: =INDEX('Projection Data'!$D$27:$AF$27,1,MATCH(A13,'Projection Data'!$D$2:$AF$2,0))*1000 -> 2159722.2 | G13: =INDEX('Projection Data'!$D$28:$AF$28,1,MATCH(A13,'Projection Data'!$D$2:$AF$2,0))*1000 -> 86388.887 | H13: =INDEX('Projection Data'!$D$20:$AF$20,1,MATCH(A13,'Projection Data'!$D$2:$AF$2,0)) -> ✅ SAFE - $0 IRMAA
A14: 67 | B14: =INDEX('Projection Data'!$D$1:$AF$1,1,MATCH(A14,'Projection Data'!$D$2:$AF$2,0)) -> 52962 | C14: =INDEX('Projection Data'!$D$21:$AF$21,1,MATCH(A14,'Projection Data'!$D$2:$AF$2,0))*1000 -> 65628 | D14: =INDEX('Projection Data'!$D$18:$AF$18,1,MATCH(A14,'Projection Data'!$D$2:$AF$2,0))*1000 -> 61.4 | E14: =INDEX('Projection Data'!$D$23:$AF$23,1,MATCH(A14,'Projection Data'!$D$2:$AF$2,0))*1000 -> 5463.8833 | F14: =INDEX('Projection Data'!$D$27:$AF$27,1,MATCH(A14,'Projection Data'!$D$2:$AF$2,0))*1000 -> 2403796.4 | G14: =INDEX('Projection Data'!$D$28:$AF$28,1,MATCH(A14,'Projection Data'!$D$2:$AF$2,0))*1000 -> 96151.858 | H14: =INDEX('Projection Data'!$D$20:$AF$20,1,MATCH(A14,'Projection Data'!$D$2:$AF$2,0)) -> ✅ SAFE - $0 IRMAA
A15: 70 | B15: =INDEX('Projection Data'!$D$1:$AF$1,1,MATCH(A15,'Projection Data'!$D$2:$AF$2,0)) -> 54057 | C15: =INDEX('Projection Data'!$D$21:$AF$21,1,MATCH(A15,'Projection Data'!$D$2:$AF$2,0))*1000 -> 65628 | D15: =INDEX('Projection Data'!$D$18:$AF$18,1,MATCH(A15,'Projection Data'!$D$2:$AF$2,0))*1000 -> 61.4 | E15: =INDEX('Projection Data'!$D$23:$AF$23,1,MATCH(A15,'Projection Data'!$D$2:$AF$2,0))*1000 -> 5463.8833 | F15: =INDEX('Projection Data'!$D$27:$AF$27,1,MATCH(A15,'Projection Data'!$D$2:$AF$2,0))*1000 -> 2965443.1 | G15: =INDEX('Projection Data'!$D$28:$AF$28,1,MATCH(A15,'Projection Data'!$D$2:$AF$2,0))*1000 -> 118617.72 | H15: =INDEX('Projection Data'!$D$20:$AF$20,1,MATCH(A15,'Projection Data'!$D$2:$AF$2,0)) -> ✅ SAFE - $0 IRMAA
A16: 75 | B16: =INDEX('Projection Data'!$D$1:$AF$1,1,MATCH(A16,'Projection Data'!$D$2:$AF$2,0)) -> 55884 | C16: =INDEX('Projection Data'!$D$21:$AF$21,1,MATCH(A16,'Projection Data'!$D$2:$AF$2,0))*1000 -> 136377.72 | D16: =INDEX('Projection Data'!$D$18:$AF$18,1,MATCH(A16,'Projection Data'!$D$2:$AF$2,0))*1000 -> 10824.023 | E16: =INDEX('Projection Data'!$D$23:$AF$23,1,MATCH(A16,'Projection Data'!$D$2:$AF$2,0))*1000 -> 10462.808 | F16: =INDEX('Projection Data'!$D$27:$AF$27,1,MATCH(A16,'Projection Data'!$D$2:$AF$2,0))*1000 -> 4208003.5 | G16: =INDEX('Projection Data'!$D$28:$AF$28,1,MATCH(A16,'Projection Data'!$D$2:$AF$2,0))*1000 -> 168320.14 | H16: =INDEX('Projection Data'!$D$20:$AF$20,1,MATCH(A16,'Projection Data'!$D$2:$AF$2,0)) -> ✅ SAFE - $0 IRMAA
A17: 77 | B17: =INDEX('Projection Data'!$D$1:$AF$1,1,MATCH(A17,'Projection Data'!$D$2:$AF$2,0)) -> 56614 | C17: =INDEX('Projection Data'!$D$21:$AF$21,1,MATCH(A17,'Projection Data'!$D$2:$AF$2,0))*1000 -> 146427.18 | D17: =INDEX('Projection Data'!$D$18:$AF$18,1,MATCH(A17,'Projection Data'!$D$2:$AF$2,0))*1000 -> 12388.256 | E17: =INDEX('Projection Data'!$D$23:$AF$23,1,MATCH(A17,'Projection Data'!$D$2:$AF$2,0))*1000 -> 11169.91 | F17: =INDEX('Projection Data'!$D$27:$AF$27,1,MATCH(A17,'Projection Data'!$D$2:$AF$2,0))*1000 -> 4688627.9 | G17: =INDEX('Projection Data'!$D$28:$AF$28,1,MATCH(A17,'Projection Data'!$D$2:$AF$2,0))*1000 -> 187545.12 | H17: =INDEX('Projection Data'!$D$20:$AF$20,1,MATCH(A17,'Projection Data'!$D$2:$AF$2,0)) -> ✅ SAFE - $0 IRMAA
A19: KEY FINDINGS
A20: ="1. Total savings rise from "&TEXT(INDEX('Projection Data'!$D$27:$AF$27,1,MATCH(49,'Projection Data'!$D$2:$AF$2,0))*1000,"$#,##0")&" at age 49 to "&TEXT('Projection Data'!AF27*1000,"$#,##0")&" at age 77 under the current assumptions." -> 1. Total savings rise from $550,000 at age 49 to $4,688,628 at age 77 under the current assumptions.
A21: ="2. Social Security begins at age "&Assumptions!B7&", with approximately "&TEXT(INDEX('Projection Data'!$D$23:$AF$23,1,MATCH(Assumptions!B7,'Projection Data'!$D$2:$AF$2,0))*1000,"$#,##0")&" of after-tax cash per month in that year." -> 2. Social Security begins at age 67, with approximately $5,464 of after-tax cash per month in that year.
A22: ="3. The first modeled required minimum distribution is "&TEXT(INDEX('Projection Data'!$D$8:$AF$8,1,MATCH(75,'Projection Data'!$D$2:$AF$2,0))*1000,"$#,##0")&" at age 75." -> 3. The first modeled required minimum distribution is $70,750 at age 75.

Sheet Assumptions
A1: RETIREMENT MODEL ASSUMPTIONS
A2: Editable inputs and supporting schedules; model financial amounts are in $000 unless noted.
A4: Key assumption | B4: Value | E4: Annual spending category | F4: Amount ($000)
A5: Annual investment return | B5: 0.0725 | E5: House | F5: 20
A6: Sustainable withdrawal rate | B6: 0.04 | E6: Transportation | F6: 6
A7: Social Security claim age | B7: 67 | E7: Health | F7: 1
A8: IRMAA MAGI threshold ($000) | B8: 218 | E8: Roth Contribution | F8: 0
A9: Tax calculation | B9: Embedded model estimate | E9: Food + entertainment + vacations | F9: 35
A10: RMD age | B10: Divisor | C10: Implied rate | E10: Total annual spending | F10: =SUM(F5:F9) -> 62
A11: 72 | B11: 27.4 | C11: =1/B11 -> 0.03649635
A12: 73 | B12: 26.5 | C12: =1/B12 -> 0.037735849
A13: 74 | B13: 25.5 | C13: =1/B13 -> 0.039215686
A14: 75 | B14: 24.6 | C14: =1/B14 -> 0.040650407
A15: 76 | B15: 23.7 | C15: =1/B15 -> 0.042194093
A16: 77 | B16: 22.9 | C16: =1/B16 -> 0.043668122
A17: 78 | B17: 22 | C17: =1/B17 -> 0.045454545
A18: 79 | B18: 21.1 | C18: =1/B18 -> 0.047393365
A19: 80 | B19: 20.2 | C19: =1/B19 -> 0.04950495
A20: 81 | B20: 19.4 | C20: =1/B20 -> 0.051546392
A21: 82 | B21: 18.5 | C21: =1/B21 -> 0.054054054
A22: 83 | B22: 17.7 | C22: =1/B22 -> 0.056497175
... A34: 95 | B34: 8.9 | C34: =1/B34 -> 0.11235955

Sheet Social Security
A1: SOCIAL SECURITY CLAIMING COMPARISON
A2: Compares the couple's gross benefit when the husband claims from age 62 through 70.
A4: Metric / husband claim age | B4: 62 | C4: 63 | D4: 64 | E4: 65 | F4: 66 | G4: 67 | H4: 68 | I4: 69 | J4: 70
A5: Husband monthly | B5: =ROUND($L$8*IF(B$4<67,1-MIN((67-B$4)*12,36)*5/900-MAX((67-B$4)*12-36,0)*5/1200,1+(B$4-67)*8%),0) -> 2729 | C5: =ROUND($L$8*IF(C$4<67,1-MIN((67-C$4)*12,36)*5/900-MAX((67-C$4)*12-36,0)*5/1200,1+(C$4-67)*8%),0) -> 2924 | D5: =ROUND($L$8*IF(D$4<67,1-MIN((67-D$4)*12,36)*5/900-MAX((67-D$4)*12-36,0)*5/1200,1+(D$4-67)*8%),0) -> 3119 | E5: =ROUND($L$8*IF(E$4<67,1-MIN((67-E$4)*12,36)*5/900-MAX((67-E$4)*12-36,0)*5/1200,1+(E$4-67)*8%),0) -> 3379 | F5: =ROUND($L$8*IF(F$4<67,1-MIN((67-F$4)*12,36)*5/900-MAX((67-F$4)*12-36,0)*5/1200,1+(F$4-67)*8%),0) -> 3639 | G5: =ROUND($L$8*IF(G$4<67,1-MIN((67-G$4)*12,36)*5/900-MAX((67-G$4)*12-36,0)*5/1200,1+(G$4-67)*8%),0) -> 3899 | H5: =ROUND($L$8*IF(H$4<67,1-MIN((67-H$4)*12,36)*5/900-MAX((67-H$4)*12-36,0)*5/1200,1+(H$4-67)*8%),0) -> 4211 | I5: =ROUND($L$8*IF(I$4<67,1-MIN((67-I$4)*12,36)*5/900-MAX((67-I$4)*12-36,0)*5/1200,1+(I$4-67)*8%),0) -> 4523 | J5: =ROUND($L$8*IF(J$4<67,1-MIN((67-J$4)*12,36)*5/900-MAX((67-J$4)*12-36,0)*5/1200,1+(J$4-67)*8%),0) -> 4835 | K5: Husband DOB | L5: 28158
A6: Wife monthly | B6: =_xlfn.LET(_xlpm.claim,MAX(EDATE($L$5,B$4*12),EDATE($L$6,62*12)),_xlpm.fra,EDATE($L$6,67*12),_xlpm.m,MAX(0,(YEAR(_xlpm.fra)-YEAR(_xlpm.claim))*12+MONTH(_xlpm.fra)-MONTH(_xlpm.claim)),ROUND($L$8*50%*(1-MIN(_xlpm.m,36)*25/3600-MAX(_xlpm.m-36,0)*5/1200),0)) -> 1267 | C6: =_xlfn.LET(_xlpm.claim,MAX(EDATE($L$5,C$4*12),EDATE($L$6,62*12)),_xlpm.fra,EDATE($L$6,67*12),_xlpm.m,MAX(0,(YEAR(_xlpm.fra)-YEAR(_xlpm.claim))*12+MONTH(_xlpm.fra)-MONTH(_xlpm.claim)),ROUND($L$8*50%*(1-MIN(_xlpm.m,36)*25/3600-MAX(_xlpm.m-36,0)*5/1200),0)) -> 1267 | D6: =_xlfn.LET(_xlpm.claim,MAX(EDATE($L$5,D$4*12),EDATE($L$6,62*12)),_xlpm.fra,EDATE($L$6,67*12),_xlpm.m,MAX(0,(YEAR(_xlpm.fra)-YEAR(_xlpm.claim))*12+MONTH(_xlpm.fra)-MONTH(_xlpm.claim)),ROUND($L$8*50%*(1-MIN(_xlpm.m,36)*25/3600-MAX(_xlpm.m-36,0)*5/1200),0)) -> 1267 | E6: =_xlfn.LET(_xlpm.claim,MAX(EDATE($L$5,E$4*12),EDATE($L$6,62*12)),_xlpm.fra,EDATE($L$6,67*12),_xlpm.m,MAX(0,(YEAR(_xlpm.fra)-YEAR(_xlpm.claim))*12+MONTH(_xlpm.fra)-MONTH(_xlpm.claim)),ROUND($L$8*50%*(1-MIN(_xlpm.m,36)*25/3600-MAX(_xlpm.m-36,0)*5/1200),0)) -> 1332 | F6: =_xlfn.LET(_xlpm.claim,MAX(EDATE($L$5,F$4*12),EDATE($L$6,62*12)),_xlpm.fra,EDATE($L$6,67*12),_xlpm.m,MAX(0,(YEAR(_xlpm.fra)-YEAR(_xlpm.claim))*12+MONTH(_xlpm.fra)-MONTH(_xlpm.claim)),ROUND($L$8*50%*(1-MIN(_xlpm.m,36)*25/3600-MAX(_xlpm.m-36,0)*5/1200),0)) -> 1430 | G6: =_xlfn.LET(_xlpm.claim,MAX(EDATE($L$5,G$4*12),EDATE($L$6,62*12)),_xlpm.fra,EDATE($L$6,67*12),_xlpm.m,MAX(0,(YEAR(_xlpm.fra)-YEAR(_xlpm.claim))*12+MONTH(_xlpm.fra)-MONTH(_xlpm.claim)),ROUND($L$8*50%*(1-MIN(_xlpm.m,36)*25/3600-MAX(_xlpm.m-36,0)*5/1200),0)) -> 1570 | H6: =_xlfn.LET(_xlpm.claim,MAX(EDATE($L$5,H$4*12),EDATE($L$6,62*12)),_xlpm.fra,EDATE($L$6,67*12),_xlpm.m,MAX(0,(YEAR(_xlpm.fra)-YEAR(_xlpm.claim))*12+MONTH(_xlpm.fra)-MONTH(_xlpm.claim)),ROUND($L$8*50%*(1-MIN(_xlpm.m,36)*25/3600-MAX(_xlpm.m-36,0)*5/1200),0)) -> 1733 | I6: =_xlfn.LET(_xlpm.claim,MAX(EDATE($L$5,I$4*12),EDATE($L$6,62*12)),_xlpm.fra,EDATE($L$6,67*12),_xlpm.m,MAX(0,(YEAR(_xlpm.fra)-YEAR(_xlpm.claim))*12+MONTH(_xlpm.fra)-MONTH(_xlpm.claim)),ROUND($L$8*50%*(1-MIN(_xlpm.m,36)*25/3600-MAX(_xlpm.m-36,0)*5/1200),0)) -> 1895 | J6: =_xlfn.LET(_xlpm.claim,MAX(EDATE($L$5,J$4*12),EDATE($L$6,62*12)),_xlpm.fra,EDATE($L$6,67*12),_xlpm.m,MAX(0,(YEAR(_xlpm.fra)-YEAR(_xlpm.claim))*12+MONTH(_xlpm.fra)-MONTH(_xlpm.claim)),ROUND($L$8*50%*(1-MIN(_xlpm.m,36)*25/3600-MAX(_xlpm.m-36,0)*5/1200),0)) -> 1950 | K6: Wife DOB | L6: 29012
A7: Couple monthly | B7: =B5+B6 -> 3996 | C7: =C5+C6 -> 4191 | D7: =D5+D6 -> 4386 | E7: =E5+E6 -> 4711 | F7: =F5+F6 -> 5069 | G7: =G5+G6 -> 5469 | H7: =H5+H6 -> 5944 | I7: =I5+I6 -> 6418 | J7: =J5+J6 -> 6785 | K7: Withdrawal Rate | L7: 0.04
A8: Couple Yearly | B8: =B7*12 -> 47952 | C8: =C7*12 -> 50292 | D8: =D7*12 -> 52632 | E8: =E7*12 -> 56532 | F8: =F7*12 -> 60828 | G8: =G7*12 -> 65628 | H8: =H7*12 -> 71328 | I8: =I7*12 -> 77016 | J8: =J7*12 -> 81420 | K8: Husband PIA @ 67 | L8: 3899
A9: Cumulative by H age 70 | B9: =IF(EDATE($L$5,70*12)>EDATE($L$5,B$4*12),DATEDIF(EDATE($L$5,B$4*12),EDATE($L$5,70*12),"m")*B5,0)+IF(EDATE($L$5,70*12)>MAX(EDATE($L$5,B$4*12),EDATE($L$6,62*12)),DATEDIF(MAX(EDATE($L$5,B$4*12),EDATE($L$6,62*12)),EDATE($L$5,70*12),"m")*B6,0) -> 346873 | C9: =IF(EDATE($L$5,70*12)>EDATE($L$5,C$4*12),DATEDIF(EDATE($L$5,C$4*12),EDATE($L$5,70*12),"m")*C5,0)+IF(EDATE($L$5,70*12)>MAX(EDATE($L$5,C$4*12),EDATE($L$6,62*12)),DATEDIF(MAX(EDATE($L$5,C$4*12),EDATE($L$6,62*12)),EDATE($L$5,70*12),"m")*C6,0) -> 330505 | D9: =IF(EDATE($L$5,70*12)>EDATE($L$5,D$4*12),DATEDIF(EDATE($L$5,D$4*12),EDATE($L$5,70*12),"m")*D5,0)+IF(EDATE($L$5,70*12)>MAX(EDATE($L$5,D$4*12),EDATE($L$6,62*12)),DATEDIF(MAX(EDATE($L$5,D$4*12),EDATE($L$6,62*12)),EDATE($L$5,70*12),"m")*D6,0) -> 309457 | E9: =IF(EDATE($L$5,70*12)>EDATE($L$5,E$4*12),DATEDIF(EDATE($L$5,E$4*12),EDATE($L$5,70*12),"m")*E5,0)+IF(EDATE($L$5,70*12)>MAX(EDATE($L$5,E$4*12),EDATE($L$6,62*12)),DATEDIF(MAX(EDATE($L$5,E$4*12),EDATE($L$6,62*12)),EDATE($L$5,70*12),"m")*E6,0) -> 282660 | F9: =IF(EDATE($L$5,70*12)>EDATE($L$5,F$4*12),DATEDIF(EDATE($L$5,F$4*12),EDATE($L$5,70*12),"m")*F5,0)+IF(EDATE($L$5,70*12)>MAX(EDATE($L$5,F$4*12),EDATE($L$6,62*12)),DATEDIF(MAX(EDATE($L$5,F$4*12),EDATE($L$6,62*12)),EDATE($L$5,70*12),"m")*F6,0) -> 243312 | G9: =IF(EDATE($L$5,70*12)>EDATE($L$5,G$4*12),DATEDIF(EDATE($L$5,G$4*12),EDATE($L$5,70*12),"m")*G5,0)+IF(EDATE($L$5,70*12)>MAX(EDATE($L$5,G$4*12),EDATE($L$6,62*12)),DATEDIF(MAX(EDATE($L$5,G$4*12),EDATE($L$6,62*12)),EDATE($L$5,70*12),"m")*G6,0) -> 196884 | H9: =IF(EDATE($L$5,70*12)>EDATE($L$5,H$4*12),DATEDIF(EDATE($L$5,H$4*12),EDATE($L$5,70*12),"m")*H5,0)+IF(EDATE($L$5,70*12)>MAX(EDATE($L$5,H$4*12),EDATE($L$6,62*12)),DATEDIF(MAX(EDATE($L$5,H$4*12),EDATE($L$6,62*12)),EDATE($L$5,70*12),"m")*H6,0) -> 142656 | I9: =IF(EDATE($L$5,70*12)>EDATE($L$5,I$4*12),DATEDIF(EDATE($L$5,I$4*12),EDATE($L$5,70*12),"m")*I5,0)+IF(EDATE($L$5,70*12)>MAX(EDATE($L$5,I$4*12),EDATE($L$6,62*12)),DATEDIF(MAX(EDATE($L$5,I$4*12),EDATE($L$6,62*12)),EDATE($L$5,70*12),"m")*I6,0) -> 77016 | J9: =IF(EDATE($L$5,70*12)>EDATE($L$5,J$4*12),DATEDIF(EDATE($L$5,J$4*12),EDATE($L$5,70*12),"m")*J5,0)+IF(EDATE($L$5,70*12)>MAX(EDATE($L$5,J$4*12),EDATE($L$6,62*12)),DATEDIF(MAX(EDATE($L$5,J$4*12),EDATE($L$6,62*12)),EDATE($L$5,70*12),"m")*J6,0) -> 0
A10: Cumulative by H age 75 | B10: =IF(EDATE($L$5,75*12)>EDATE($L$5,B$4*12),DATEDIF(EDATE($L$5,B$4*12),EDATE($L$5,75*12),"m")*B5,0)+IF(EDATE($L$5,75*12)>MAX(EDATE($L$5,B$4*12),EDATE($L$6,62*12)),DATEDIF(MAX(EDATE($L$5,B$4*12),EDATE($L$6,62*12)),EDATE($L$5,75*12),"m")*B6,0) -> 586633 | C10: =IF(EDATE($L$5,75*12)>EDATE($L$5,C$4*12),DATEDIF(EDATE($L$5,C$4*12),EDATE($L$5,75*12),"m")*C5,0)+IF(EDATE($L$5,75*12)>MAX(EDATE($L$5,C$4*12),EDATE($L$6,62*12)),DATEDIF(MAX(EDATE($L$5,C$4*12),EDATE($L$6,62*12)),EDATE($L$5,75*12),"m")*C6,0) -> 581965 | D10: =IF(EDATE($L$5,75*12)>EDATE($L$5,D$4*12),DATEDIF(EDATE($L$5,D$4*12),EDATE($L$5,75*12),"m")*D5,0)+IF(EDATE($L$5,75*12)>MAX(EDATE($L$5,D$4*12),EDATE($L$6,62*12)),DATEDIF(MAX(EDATE($L$5,D$4*12),EDATE($L$6,62*12)),EDATE($L$5,75*12),"m")*D6,0) -> 572617 | E10: =IF(EDATE($L$5,75*12)>EDATE($L$5,E$4*12),DATEDIF(EDATE($L$5,E$4*12),EDATE($L$5,75*12),"m")*E5,0)+IF(EDATE($L$5,75*12)>MAX(EDATE($L$5,E$4*12),EDATE($L$6,62*12)),DATEDIF(MAX(EDATE($L$5,E$4*12),EDATE($L$6,62*12)),EDATE($L$5,75*12),"m")*E6,0) -> 565320 | F10: =IF(EDATE($L$5,75*12)>EDATE($L$5,F$4*12),DATEDIF(EDATE($L$5,F$4*12),EDATE($L$5,75*12),"m")*F5,0)+IF(EDATE($L$5,75*12)>MAX(EDATE($L$5,F$4*12),EDATE($L$6,62*12)),DATEDIF(MAX(EDATE($L$5,F$4*12),EDATE($L$6,62*12)),EDATE($L$5,75*12),"m")*F6,0) -> 547452 | G10: =IF(EDATE($L$5,75*12)>EDATE($L$5,G$4*12),DATEDIF(EDATE($L$5,G$4*12),EDATE($L$5,75*12),"m")*G5,0)+IF(EDATE($L$5,75*12)>MAX(EDATE($L$5,G$4*12),EDATE($L$6,62*12)),DATEDIF(MAX(EDATE($L$5,G$4*12),EDATE($L$6,62*12)),EDATE($L$5,75*12),"m")*G6,0) -> 525024 | H10: =IF(EDATE($L$5,75*12)>EDATE($L$5,H$4*12),DATEDIF(EDATE($L$5,H$4*12),EDATE($L$5,75*12),"m")*H5,0)+IF(EDATE($L$5,75*12)>MAX(EDATE($L$5,H$4*12),EDATE($L$6,62*12)),DATEDIF(MAX(EDATE($L$5,H$4*12),EDATE($L$6,62*12)),EDATE($L$5,75*12),"m")*H6,0) -> 499296 | I10: =IF(EDATE($L$5,75*12)>EDATE($L$5,I$4*12),DATEDIF(EDATE($L$5,I$4*12),EDATE($L$5,75*12),"m")*I5,0)+IF(EDATE($L$5,75*12)>MAX(EDATE($L$5,I$4*12),EDATE($L$6,62*12)),DATEDIF(MAX(EDATE($L$5,I$4*12),EDATE($L$6,62*12)),EDATE($L$5,75*12),"m")*I6,0) -> 462096 | J10: =IF(EDATE($L$5,75*12)>EDATE($L$5,J$4*12),DATEDIF(EDATE($L$5,J$4*12),EDATE($L$5,75*12),"m")*J5,0)+IF(EDATE($L$5,75*12)>MAX(EDATE($L$5,J$4*12),EDATE($L$6,62*12)),DATEDIF(MAX(EDATE($L$5,J$4*12),EDATE($L$6,62*12)),EDATE($L$5,75*12),"m")*J6,0) -> 407100
A11: Cumulative by H age 80 | B11: =IF(EDATE($L$5,80*12)>EDATE($L$5,B$4*12),DATEDIF(EDATE($L$5,B$4*12),EDATE($L$5,80*12),"m")*B5,0)+IF(EDATE($L$5,80*12)>MAX(EDATE($L$5,B$4*12),EDATE($L$6,62*12)),DATEDIF(MAX(EDATE($L$5,B$4*12),EDATE($L$6,62*12)),EDATE($L$5,80*12),"m")*B6,0) -> 826393 | C11: =IF(EDATE($L$5,80*12)>EDATE($L$5,C$4*12),DATEDIF(EDATE($L$5,C$4*12),EDATE($L$5,80*12),"m")*C5,0)+IF(EDATE($L$5,80*12)>MAX(EDATE($L$5,C$4*12),EDATE($L$6,62*12)),DATEDIF(MAX(EDATE($L$5,C$4*12),EDATE($L$6,62*12)),EDATE($L$5,80*12),"m")*C6,0) -> 833425 | D11: =IF(EDATE($L$5,80*12)>EDATE($L$5,D$4*12),DATEDIF(EDATE($L$5,D$4*12),EDATE($L$5,80*12),"m")*D5,0)+IF(EDATE($L$5,80*12)>MAX(EDATE($L$5,D$4*12),EDATE($L$6,62*12)),DATEDIF(MAX(EDATE($L$5,D$4*12),EDATE($L$6,62*12)),EDATE($L$5,80*12),"m")*D6,0) -> 835777 | E11: =IF(EDATE($L$5,80*12)>EDATE($L$5,E$4*12),DATEDIF(EDATE($L$5,E$4*12),EDATE($L$5,80*12),"m")*E5,0)+IF(EDATE($L$5,80*12)>MAX(EDATE($L$5,E$4*12),EDATE($L$6,62*12)),DATEDIF(MAX(EDATE($L$5,E$4*12),EDATE($L$6,62*12)),EDATE($L$5,80*12),"m")*E6,0) -> 847980 | F11: =IF(EDATE($L$5,80*12)>EDATE($L$5,F$4*12),DATEDIF(EDATE($L$5,F$4*12),EDATE($L$5,80*12),"m")*F5,0)+IF(EDATE($L$5,80*12)>MAX(EDATE($L$5,F$4*12),EDATE($L$6,62*12)),DATEDIF(MAX(EDATE($L$5,F$4*12),EDATE($L$6,62*12)),EDATE($L$5,80*12),"m")*F6,0) -> 851592 | G11: =IF(EDATE($L$5,80*12)>EDATE($L$5,G$4*12),DATEDIF(EDATE($L$5,G$4*12),EDATE($L$5,80*12),"m")*G5,0)+IF(EDATE($L$5,80*12)>MAX(EDATE($L$5,G$4*12),EDATE($L$6,62*12)),DATEDIF(MAX(EDATE($L$5,G$4*12),EDATE($L$6,62*12)),EDATE($L$5,80*12),"m")*G6,0) -> 853164 | H11: =IF(EDATE($L$5,80*12)>EDATE($L$5,H$4*12),DATEDIF(EDATE($L$5,H$4*12),EDATE($L$5,80*12),"m")*H5,0)+IF(EDATE($L$5,80*12)>MAX(EDATE($L$5,H$4*12),EDATE($L$6,62*12)),DATEDIF(MAX(EDATE($L$5,H$4*12),EDATE($L$6,62*12)),EDATE($L$5,80*12),"m")*H6,0) -> 855936 | I11: =IF(EDATE($L$5,80*12)>EDATE($L$5,I$4*12),DATEDIF(EDATE($L$5,I$4*12),EDATE($L$5,80*12),"m")*I5,0)+IF(EDATE($L$5,80*12)>MAX(EDATE($L$5,I$4*12),EDATE($L$6,62*12)),DATEDIF(MAX(EDATE($L$5,I$4*12),EDATE($L$6,62*12)),EDATE($L$5,80*12),"m")*I6,0) -> 847176 | J11: =IF(EDATE($L$5,80*12)>EDATE($L$5,J$4*12),DATEDIF(EDATE($L$5,J$4*12),EDATE($L$5,80*12),"m")*J5,0)+IF(EDATE($L$5,80*12)>MAX(EDATE($L$5,J$4*12),EDATE($L$6,62*12)),DATEDIF(MAX(EDATE($L$5,J$4*12),EDATE($L$6,62*12)),EDATE($L$5,80*12),"m")*J6,0) -> 814200
A12: Cumulative by H age 85 | B12: =IF(EDATE($L$5,85*12)>EDATE($L$5,B$4*12),DATEDIF(EDATE($L$5,B$4*12),EDATE($L$5,85*12),"m")*B5,0)+IF(EDATE($L$5,85*12)>MAX(EDATE($L$5,B$4*12),EDATE($L$6,62*12)),DATEDIF(MAX(EDATE($L$5,B$4*12),EDATE($L$6,62*12)),EDATE($L$5,85*12),"m")*B6,0) -> 1066153 | C12: =IF(EDATE($L$5,85*12)>EDATE($L$5,C$4*12),DATEDIF(EDATE($L$5,C$4*12),EDATE($L$5,85*12),"m")*C5,0)+IF(EDATE($L$5,85*12)>MAX(EDATE($L$5,C$4*12),EDATE($L$6,62*12)),DATEDIF(MAX(EDATE($L$5,C$4*12),EDATE($L$6,62*12)),EDATE($L$5,85*12),"m")*C6,0) -> 1084885 | D12: =IF(EDATE($L$5,85*12)>EDATE($L$5,D$4*12),DATEDIF(EDATE($L$5,D$4*12),EDATE($L$5,85*12),"m")*D5,0)+IF(EDATE($L$5,85*12)>MAX(EDATE($L$5,D$4*12),EDATE($L$6,62*12)),DATEDIF(MAX(EDATE($L$5,D$4*12),EDATE($L$6,62*12)),EDATE($L$5,85*12),"m")*D6,0) -> 1098937 | E12: =IF(EDATE($L$5,85*12)>EDATE($L$5,E$4*12),DATEDIF(EDATE($L$5,E$4*12),EDATE($L$5,85*12),"m")*E5,0)+IF(EDATE($L$5,85*12)>MAX(EDATE($L$5,E$4*12),EDATE($L$6,62*12)),DATEDIF(MAX(EDATE($L$5,E$4*12),EDATE($L$6,62*12)),EDATE($L$5,85*12),"m")*E6,0) -> 1130640 | F12: =IF(EDATE($L$5,85*12)>EDATE($L$5,F$4*12),DATEDIF(EDATE($L$5,F$4*12),EDATE($L$5,85*12),"m")*F5,0)+IF(EDATE($L$5,85*12)>MAX(EDATE($L$5,F$4*12),EDATE($L$6,62*12)),DATEDIF(MAX(EDATE($L$5,F$4*12),EDATE($L$6,62*12)),EDATE($L$5,85*12),"m")*F6,0) -> 1155732 | G12: =IF(EDATE($L$5,85*12)>EDATE($L$5,G$4*12),DATEDIF(EDATE($L$5,G$4*12),EDATE($L$5,85*12),"m")*G5,0)+IF(EDATE($L$5,85*12)>MAX(EDATE($L$5,G$4*12),EDATE($L$6,62*12)),DATEDIF(MAX(EDATE($L$5,G$4*12),EDATE($L$6,62*12)),EDATE($L$5,85*12),"m")*G6,0) -> 1181304 | H12: =IF(EDATE($L$5,85*12)>EDATE($L$5,H$4*12),DATEDIF(EDATE($L$5,H$4*12),EDATE($L$5,85*12),"m")*H5,0)+IF(EDATE($L$5,85*12)>MAX(EDATE($L$5,H$4*12),EDATE($L$6,62*12)),DATEDIF(MAX(EDATE($L$5,H$4*12),EDATE($L$6,62*12)),EDATE($L$5,85*12),"m")*H6,0) -> 1212576 | I12: =IF(EDATE($L$5,85*12)>EDATE($L$5,I$4*12),DATEDIF(EDATE($L$5,I$4*12),EDATE($L$5,85*12),"m")*I5,0)+IF(EDATE($L$5,85*12)>MAX(EDATE($L$5,I$4*12),EDATE($L$6,62*12)),DATEDIF(MAX(EDATE($L$5,I$4*12),EDATE($L$6,62*12)),EDATE($L$5,85*12),"m")*I6,0) -> 1232256 | J12: =IF(EDATE($L$5,85*12)>EDATE($L$5,J$4*12),DATEDIF(EDATE($L$5,J$4*12),EDATE($L$5,85*12),"m")*J5,0)+IF(EDATE($L$5,85*12)>MAX(EDATE($L$5,J$4*12),EDATE($L$6,62*12)),DATEDIF(MAX(EDATE($L$5,J$4*12),EDATE($L$6,62*12)),EDATE($L$5,85*12),"m")*J6,0) -> 1221300
A13: Assumption: wife claims at her first eligible month after husband files. MFJ affects taxation, not gross SSA benefits. Values exclude COLA, tax, investment return, survivor benefits, and the earnings test.
